csmpy/__init__.py
csmpy/colors.py
csmpy/csmpy.py
csmpy/utils.py
csmpy-0.2.dist-info/LICENSE
csmpy-0.2.dist-info/METADATA
csmpy-0.2.dist-info/WHEEL
csmpy-0.2.dist-info/top_level.txt
csmpy-0.2.dist-info/RECORD
