Metadata-Version: 2.1
Name: csmpy
Version: 0.2
Summary: Color scheme manager package for your projects
Home-page: https://github.com/endormi/csm
Author: Endormi
License: MIT
Classifier: Programming Language :: Python :: 3
Classifier: License :: OSI Approved :: MIT License
Classifier: Operating System :: OS Independent
Requires-Python: >=3
License-File: LICENSE
Requires-Dist: PyYAML
